{
  "type": "File",
  "start": 0,
  "end": 137,
  "loc": {
    "start": {
      "line": 1,
      "column": 0
    },
    "end": {
      "line": 4,
      "column": 0
    }
  },
  "program": {
    "type": "Program",
    "start": 0,
    "end": 137,
    "loc": {
      "start": {
        "line": 1,
        "column": 0
      },
      "end": {
        "line": 4,
        "column": 0
      }
    },
    "sourceType": "module",
    "body": [
      {
        "type": "ExportDefaultDeclaration",
        "start": 0,
        "end": 136,
        "loc": {
          "start": {
            "line": 1,
            "column": 0
          },
          "end": {
            "line": 3,
            "column": 1
          }
        },
        "declaration": {
          "type": "FunctionDeclaration",
          "start": 15,
          "end": 136,
          "loc": {
            "start": {
              "line": 1,
              "column": 15
            },
            "end": {
              "line": 3,
              "column": 1
            }
          },
          "id": {
            "type": "Identifier",
            "start": 24,
            "end": 49,
            "loc": {
              "start": {
                "line": 1,
                "column": 24
              },
              "end": {
                "line": 1,
                "column": 49
              },
              "identifierName": "getDefaultMapKeyDelimiter"
            },
            "name": "getDefaultMapKeyDelimiter"
          },
          "generator": false,
          "expression": false,
          "async": false,
          "params": [
            {
              "type": "Identifier",
              "start": 50,
              "end": 75,
              "loc": {
                "start": {
                  "line": 1,
                  "column": 50
                },
                "end": {
                  "line": 1,
                  "column": 75
                },
                "identifierName": "currentIncarnateDelimiter"
              },
              "name": "currentIncarnateDelimiter"
            }
          ],
          "body": {
            "type": "BlockStatement",
            "start": 77,
            "end": 136,
            "loc": {
              "start": {
                "line": 1,
                "column": 77
              },
              "end": {
                "line": 3,
                "column": 1
              }
            },
            "body": [
              {
                "type": "ReturnStatement",
                "start": 81,
                "end": 134,
                "loc": {
                  "start": {
                    "line": 2,
                    "column": 2
                  },
                  "end": {
                    "line": 2,
                    "column": 55
                  }
                },
                "argument": {
                  "type": "ConditionalExpression",
                  "start": 88,
                  "end": 133,
                  "loc": {
                    "start": {
                      "line": 2,
                      "column": 9
                    },
                    "end": {
                      "line": 2,
                      "column": 54
                    }
                  },
                  "test": {
                    "type": "BinaryExpression",
                    "start": 88,
                    "end": 121,
                    "loc": {
                      "start": {
                        "line": 2,
                        "column": 9
                      },
                      "end": {
                        "line": 2,
                        "column": 42
                      }
                    },
                    "left": {
                      "type": "Identifier",
                      "start": 88,
                      "end": 113,
                      "loc": {
                        "start": {
                          "line": 2,
                          "column": 9
                        },
                        "end": {
                          "line": 2,
                          "column": 34
                        },
                        "identifierName": "currentIncarnateDelimiter"
                      },
                      "name": "currentIncarnateDelimiter"
                    },
                    "operator": "===",
                    "right": {
                      "type": "StringLiteral",
                      "start": 118,
                      "end": 121,
                      "loc": {
                        "start": {
                          "line": 2,
                          "column": 39
                        },
                        "end": {
                          "line": 2,
                          "column": 42
                        }
                      },
                      "extra": {
                        "rawValue": ".",
                        "raw": "'.'"
                      },
                      "value": "."
                    }
                  },
                  "consequent": {
                    "type": "StringLiteral",
                    "start": 124,
                    "end": 127,
                    "loc": {
                      "start": {
                        "line": 2,
                        "column": 45
                      },
                      "end": {
                        "line": 2,
                        "column": 48
                      }
                    },
                    "extra": {
                      "rawValue": "|",
                      "raw": "'|'"
                    },
                    "value": "|"
                  },
                  "alternate": {
                    "type": "StringLiteral",
                    "start": 130,
                    "end": 133,
                    "loc": {
                      "start": {
                        "line": 2,
                        "column": 51
                      },
                      "end": {
                        "line": 2,
                        "column": 54
                      }
                    },
                    "extra": {
                      "rawValue": ".",
                      "raw": "'.'"
                    },
                    "value": "."
                  }
                }
              }
            ],
            "directives": []
          },
          "leadingComments": [],
          "trailingComments": []
        }
      }
    ],
    "directives": []
  },
  "comments": [],
  "tokens": [
    {
      "type": {
        "label": "export",
        "keyword": "export",
        "beforeExpr": false,
        "startsExpr": false,
        "rightAssociative": false,
        "isLoop": false,
        "isAssign": false,
        "prefix": false,
        "postfix": false,
        "binop": null,
        "updateContext": null
      },
      "value": "export",
      "start": 0,
      "end": 6,
      "loc": {
        "start": {
          "line": 1,
          "column": 0
        },
        "end": {
          "line": 1,
          "column": 6
        }
      }
    },
    {
      "type": {
        "label": "default",
        "keyword": "default",
        "beforeExpr": true,
        "startsExpr": false,
        "rightAssociative": false,
        "isLoop": false,
        "isAssign": false,
        "prefix": false,
        "postfix": false,
        "binop": null,
        "updateContext": null
      },
      "value": "default",
      "start": 7,
      "end": 14,
      "loc": {
        "start": {
          "line": 1,
          "column": 7
        },
        "end": {
          "line": 1,
          "column": 14
        }
      }
    },
    {
      "type": {
        "label": "function",
        "keyword": "function",
        "beforeExpr": false,
        "startsExpr": true,
        "rightAssociative": false,
        "isLoop": false,
        "isAssign": false,
        "prefix": false,
        "postfix": false,
        "binop": null
      },
      "value": "function",
      "start": 15,
      "end": 23,
      "loc": {
        "start": {
          "line": 1,
          "column": 15
        },
        "end": {
          "line": 1,
          "column": 23
        }
      }
    },
    {
      "type": {
        "label": "name",
        "beforeExpr": false,
        "startsExpr": true,
        "rightAssociative": false,
        "isLoop": false,
        "isAssign": false,
        "prefix": false,
        "postfix": false,
        "binop": null
      },
      "value": "getDefaultMapKeyDelimiter",
      "start": 24,
      "end": 49,
      "loc": {
        "start": {
          "line": 1,
          "column": 24
        },
        "end": {
          "line": 1,
          "column": 49
        }
      }
    },
    {
      "type": {
        "label": "(",
        "beforeExpr": true,
        "startsExpr": true,
        "rightAssociative": false,
        "isLoop": false,
        "isAssign": false,
        "prefix": false,
        "postfix": false,
        "binop": null
      },
      "start": 49,
      "end": 50,
      "loc": {
        "start": {
          "line": 1,
          "column": 49
        },
        "end": {
          "line": 1,
          "column": 50
        }
      }
    },
    {
      "type": {
        "label": "name",
        "beforeExpr": false,
        "startsExpr": true,
        "rightAssociative": false,
        "isLoop": false,
        "isAssign": false,
        "prefix": false,
        "postfix": false,
        "binop": null
      },
      "value": "currentIncarnateDelimiter",
      "start": 50,
      "end": 75,
      "loc": {
        "start": {
          "line": 1,
          "column": 50
        },
        "end": {
          "line": 1,
          "column": 75
        }
      }
    },
    {
      "type": {
        "label": ")",
        "beforeExpr": false,
        "startsExpr": false,
        "rightAssociative": false,
        "isLoop": false,
        "isAssign": false,
        "prefix": false,
        "postfix": false,
        "binop": null
      },
      "start": 75,
      "end": 76,
      "loc": {
        "start": {
          "line": 1,
          "column": 75
        },
        "end": {
          "line": 1,
          "column": 76
        }
      }
    },
    {
      "type": {
        "label": "{",
        "beforeExpr": true,
        "startsExpr": true,
        "rightAssociative": false,
        "isLoop": false,
        "isAssign": false,
        "prefix": false,
        "postfix": false,
        "binop": null
      },
      "start": 77,
      "end": 78,
      "loc": {
        "start": {
          "line": 1,
          "column": 77
        },
        "end": {
          "line": 1,
          "column": 78
        }
      }
    },
    {
      "type": {
        "label": "return",
        "keyword": "return",
        "beforeExpr": true,
        "startsExpr": false,
        "rightAssociative": false,
        "isLoop": false,
        "isAssign": false,
        "prefix": false,
        "postfix": false,
        "binop": null,
        "updateContext": null
      },
      "value": "return",
      "start": 81,
      "end": 87,
      "loc": {
        "start": {
          "line": 2,
          "column": 2
        },
        "end": {
          "line": 2,
          "column": 8
        }
      }
    },
    {
      "type": {
        "label": "name",
        "beforeExpr": false,
        "startsExpr": true,
        "rightAssociative": false,
        "isLoop": false,
        "isAssign": false,
        "prefix": false,
        "postfix": false,
        "binop": null
      },
      "value": "currentIncarnateDelimiter",
      "start": 88,
      "end": 113,
      "loc": {
        "start": {
          "line": 2,
          "column": 9
        },
        "end": {
          "line": 2,
          "column": 34
        }
      }
    },
    {
      "type": {
        "label": "==/!=",
        "beforeExpr": true,
        "startsExpr": false,
        "rightAssociative": false,
        "isLoop": false,
        "isAssign": false,
        "prefix": false,
        "postfix": false,
        "binop": 6,
        "updateContext": null
      },
      "value": "===",
      "start": 114,
      "end": 117,
      "loc": {
        "start": {
          "line": 2,
          "column": 35
        },
        "end": {
          "line": 2,
          "column": 38
        }
      }
    },
    {
      "type": {
        "label": "string",
        "beforeExpr": false,
        "startsExpr": true,
        "rightAssociative": false,
        "isLoop": false,
        "isAssign": false,
        "prefix": false,
        "postfix": false,
        "binop": null,
        "updateContext": null
      },
      "value": ".",
      "start": 118,
      "end": 121,
      "loc": {
        "start": {
          "line": 2,
          "column": 39
        },
        "end": {
          "line": 2,
          "column": 42
        }
      }
    },
    {
      "type": {
        "label": "?",
        "beforeExpr": true,
        "startsExpr": false,
        "rightAssociative": false,
        "isLoop": false,
        "isAssign": false,
        "prefix": false,
        "postfix": false,
        "binop": null,
        "updateContext": null
      },
      "start": 122,
      "end": 123,
      "loc": {
        "start": {
          "line": 2,
          "column": 43
        },
        "end": {
          "line": 2,
          "column": 44
        }
      }
    },
    {
      "type": {
        "label": "string",
        "beforeExpr": false,
        "startsExpr": true,
        "rightAssociative": false,
        "isLoop": false,
        "isAssign": false,
        "prefix": false,
        "postfix": false,
        "binop": null,
        "updateContext": null
      },
      "value": "|",
      "start": 124,
      "end": 127,
      "loc": {
        "start": {
          "line": 2,
          "column": 45
        },
        "end": {
          "line": 2,
          "column": 48
        }
      }
    },
    {
      "type": {
        "label": ":",
        "beforeExpr": true,
        "startsExpr": false,
        "rightAssociative": false,
        "isLoop": false,
        "isAssign": false,
        "prefix": false,
        "postfix": false,
        "binop": null,
        "updateContext": null
      },
      "start": 128,
      "end": 129,
      "loc": {
        "start": {
          "line": 2,
          "column": 49
        },
        "end": {
          "line": 2,
          "column": 50
        }
      }
    },
    {
      "type": {
        "label": "string",
        "beforeExpr": false,
        "startsExpr": true,
        "rightAssociative": false,
        "isLoop": false,
        "isAssign": false,
        "prefix": false,
        "postfix": false,
        "binop": null,
        "updateContext": null
      },
      "value": ".",
      "start": 130,
      "end": 133,
      "loc": {
        "start": {
          "line": 2,
          "column": 51
        },
        "end": {
          "line": 2,
          "column": 54
        }
      }
    },
    {
      "type": {
        "label": ";",
        "beforeExpr": true,
        "startsExpr": false,
        "rightAssociative": false,
        "isLoop": false,
        "isAssign": false,
        "prefix": false,
        "postfix": false,
        "binop": null,
        "updateContext": null
      },
      "start": 133,
      "end": 134,
      "loc": {
        "start": {
          "line": 2,
          "column": 54
        },
        "end": {
          "line": 2,
          "column": 55
        }
      }
    },
    {
      "type": {
        "label": "}",
        "beforeExpr": false,
        "startsExpr": false,
        "rightAssociative": false,
        "isLoop": false,
        "isAssign": false,
        "prefix": false,
        "postfix": false,
        "binop": null
      },
      "start": 135,
      "end": 136,
      "loc": {
        "start": {
          "line": 3,
          "column": 0
        },
        "end": {
          "line": 3,
          "column": 1
        }
      }
    },
    {
      "type": {
        "label": "eof",
        "beforeExpr": false,
        "startsExpr": false,
        "rightAssociative": false,
        "isLoop": false,
        "isAssign": false,
        "prefix": false,
        "postfix": false,
        "binop": null,
        "updateContext": null
      },
      "start": 137,
      "end": 137,
      "loc": {
        "start": {
          "line": 4,
          "column": 0
        },
        "end": {
          "line": 4,
          "column": 0
        }
      }
    }
  ]
}